calcweaver/__init__.py
calcweaver/error.py
calcweaver/graph.py
calcweaver/knot.py
calcweaver/parser.py
calcweaver/utils.py
calcweaver/visualize.py
calcweaver/weave.py
calcweaver-0.1.1a0.dist-info/LICENSE
calcweaver-0.1.1a0.dist-info/METADATA
calcweaver-0.1.1a0.dist-info/WHEEL
calcweaver-0.1.1a0.dist-info/RECORD
