Metadata-Version: 2.1
Name: calcweaver
Version: 0.1.1a0
Summary: 
Author: Vishal Kumar
Requires-Python: >=3.8,<4.0
Classifier: Programming Language :: Python :: 3
Classifier: Programming Language :: Python :: 3.8
Classifier: Programming Language :: Python :: 3.9
Classifier: Programming Language :: Python :: 3.10
Classifier: Programming Language :: Python :: 3.11
Classifier: Programming Language :: Python :: 3.12
Requires-Dist: graphviz[all] (>=0.20.1)
